{
	"info": {
		"_postman_id": "8760a5ea-e903-41f0-885f-75c2bcea41ee",
		"name": "Deadman",
		"schema": "https://schema.getpostman.com/json/collection/v2.1.0/collection.json"
	},
	"item": [
		{
			"name": "Login",
			"request": {
				"method": "POST",
				"header": [],
				"body": {
					"mode": "formdata",
					"formdata": [
						{
							"key": "username",
							"value": "reritom",
							"description": "",
							"type": "text"
						},
						{
							"key": "password",
							"value": "testpassword",
							"description": "",
							"type": "text"
						}
					]
				},
				"url": {
					"raw": "http://127.0.0.1:8000/login",
					"protocol": "http",
					"host": [
						"127",
						"0",
						"0",
						"1"
					],
					"port": "8000",
					"path": [
						"login"
					]
				}
			},
			"response": []
		},
		{
			"name": "Signup",
			"request": {
				"method": "POST",
				"header": [],
				"body": {
					"mode": "formdata",
					"formdata": [
						{
							"key": "username",
							"value": "reritom",
							"description": "",
							"type": "text"
						},
						{
							"key": "password",
							"value": "testpassword",
							"description": "",
							"type": "text"
						},
						{
							"key": "email",
							"value": "test@gmail.com",
							"description": "",
							"type": "text"
						}
					]
				},
				"url": {
					"raw": "http://127.0.0.1:8000/signup",
					"protocol": "http",
					"host": [
						"127",
						"0",
						"0",
						"1"
					],
					"port": "8000",
					"path": [
						"signup"
					]
				}
			},
			"response": []
		},
		{
			"name": "Logout",
			"request": {
				"method": "GET",
				"header": [],
				"body": {},
				"url": {
					"raw": "http://127.0.0.1:8000/logout",
					"protocol": "http",
					"host": [
						"127",
						"0",
						"0",
						"1"
					],
					"port": "8000",
					"path": [
						"logout"
					]
				}
			},
			"response": []
		},
		{
			"name": "Create Contact",
			"request": {
				"method": "POST",
				"header": [],
				"body": {
					"mode": "formdata",
					"formdata": [
						{
							"key": "name",
							"value": "Jack Black",
							"description": "",
							"type": "text"
						},
						{
							"key": "phone_number",
							"value": "097548930",
							"description": "",
							"type": "text"
						},
						{
							"key": "email_address",
							"value": "thero@gmail.com",
							"description": "",
							"type": "text"
						}
					]
				},
				"url": {
					"raw": "http://127.0.0.1:8000/contact",
					"protocol": "http",
					"host": [
						"127",
						"0",
						"0",
						"1"
					],
					"port": "8000",
					"path": [
						"contact"
					]
				}
			},
			"response": []
		},
		{
			"name": "Get All Contacts",
			"request": {
				"method": "GET",
				"header": [],
				"body": {},
				"url": {
					"raw": "http://127.0.0.1:8000/contact",
					"protocol": "http",
					"host": [
						"127",
						"0",
						"0",
						"1"
					],
					"port": "8000",
					"path": [
						"contact"
					]
				}
			},
			"response": []
		},
		{
			"name": "Get Contact By ID",
			"request": {
				"method": "GET",
				"header": [],
				"body": {},
				"url": {
					"raw": "http://127.0.0.1:8000/contact/9904ab18-9aaa-48c0-9989-75478fbb830d",
					"protocol": "http",
					"host": [
						"127",
						"0",
						"0",
						"1"
					],
					"port": "8000",
					"path": [
						"contact",
						"9904ab18-9aaa-48c0-9989-75478fbb830d"
					]
				}
			},
			"response": []
		},
		{
			"name": "Update Existing Contact",
			"request": {
				"method": "POST",
				"header": [],
				"body": {
					"mode": "formdata",
					"formdata": [
						{
							"key": "email_address",
							"value": "a_new_address_again@gmail.com",
							"description": "",
							"type": "text"
						}
					]
				},
				"url": {
					"raw": "http://127.0.0.1:8000/contact/08595fe5-e690-4e41-a9d3-38c6ddd987b9",
					"protocol": "http",
					"host": [
						"127",
						"0",
						"0",
						"1"
					],
					"port": "8000",
					"path": [
						"contact",
						"08595fe5-e690-4e41-a9d3-38c6ddd987b9"
					]
				}
			},
			"response": []
		},
		{
			"name": "Update Existing Contact (Remove)",
			"request": {
				"method": "POST",
				"header": [],
				"body": {
					"mode": "formdata",
					"formdata": [
						{
							"key": "email_address",
							"value": "thero@gmail.com",
							"description": "",
							"type": "text"
						},
						{
							"key": "mode",
							"value": "REMOVE",
							"description": "",
							"type": "text"
						}
					]
				},
				"url": {
					"raw": "http://127.0.0.1:8000/contact/9904ab18-9aaa-48c0-9989-75478fbb830d",
					"protocol": "http",
					"host": [
						"127",
						"0",
						"0",
						"1"
					],
					"port": "8000",
					"path": [
						"contact",
						"9904ab18-9aaa-48c0-9989-75478fbb830d"
					]
				}
			},
			"response": []
		},
		{
			"name": "Delete Contact",
			"request": {
				"method": "DELETE",
				"header": [],
				"body": {},
				"url": {
					"raw": "http://127.0.0.1:8000/contact/9904ab18-9aaa-48c0-9989-75478fbb830d",
					"protocol": "http",
					"host": [
						"127",
						"0",
						"0",
						"1"
					],
					"port": "8000",
					"path": [
						"contact",
						"9904ab18-9aaa-48c0-9989-75478fbb830d"
					]
				}
			},
			"response": []
		},
		{
			"name": "Create Message",
			"request": {
				"method": "POST",
				"header": [],
				"body": {
					"mode": "formdata",
					"formdata": [
						{
							"key": "subject",
							"value": "To you",
							"description": "",
							"type": "text"
						},
						{
							"key": "message",
							"value": "Another test message",
							"description": "",
							"type": "text"
						},
						{
							"key": "cutoff",
							"value": "10",
							"description": "",
							"type": "text"
						},
						{
							"key": "recipient",
							"value": "05076184-a393-430b-8950-bb8588d07314",
							"description": "",
							"type": "text"
						},
						{
							"key": "lifespan",
							"value": "5",
							"description": "",
							"type": "text"
						},
						{
							"key": "viewable",
							"value": "True",
							"description": "",
							"type": "text"
						},
						{
							"key": "deletable",
							"value": "True",
							"description": "",
							"type": "text"
						}
					]
				},
				"url": {
					"raw": "http://127.0.0.1:8000/message",
					"protocol": "http",
					"host": [
						"127",
						"0",
						"0",
						"1"
					],
					"port": "8000",
					"path": [
						"message"
					]
				}
			},
			"response": []
		},
		{
			"name": "Get All Messages",
			"request": {
				"method": "GET",
				"header": [],
				"body": {},
				"url": {
					"raw": "http://127.0.0.1:8000/message",
					"protocol": "http",
					"host": [
						"127",
						"0",
						"0",
						"1"
					],
					"port": "8000",
					"path": [
						"message"
					]
				}
			},
			"response": []
		},
		{
			"name": "Get Message",
			"request": {
				"method": "GET",
				"header": [],
				"body": {},
				"url": {
					"raw": "http://127.0.0.1:8000/message/f54f37be-37bb-4eb6-a731-3838c3cc49de",
					"protocol": "http",
					"host": [
						"127",
						"0",
						"0",
						"1"
					],
					"port": "8000",
					"path": [
						"message",
						"f54f37be-37bb-4eb6-a731-3838c3cc49de"
					]
				}
			},
			"response": []
		},
		{
			"name": "Add Contact To Message",
			"request": {
				"method": "POST",
				"header": [],
				"body": {
					"mode": "formdata",
					"formdata": [
						{
							"key": "recipient",
							"value": "a664cc1f-6b3e-4fd2-8b1b-1843f417c584",
							"description": "",
							"type": "text"
						},
						{
							"key": "mode",
							"value": "UPDATE",
							"description": "",
							"type": "text"
						}
					]
				},
				"url": {
					"raw": "http://127.0.0.1:8000/message/2152d20f-a426-402f-bebd-72d5d2798dd8",
					"protocol": "http",
					"host": [
						"127",
						"0",
						"0",
						"1"
					],
					"port": "8000",
					"path": [
						"message",
						"2152d20f-a426-402f-bebd-72d5d2798dd8"
					]
				}
			},
			"response": []
		},
		{
			"name": "Add Contact To Message (Remove)",
			"request": {
				"method": "POST",
				"header": [],
				"body": {
					"mode": "formdata",
					"formdata": [
						{
							"key": "recipient",
							"value": "a664cc1f-6b3e-4fd2-8b1b-1843f417c584",
							"description": "",
							"type": "text"
						},
						{
							"key": "mode",
							"value": "REMOVE",
							"description": "",
							"type": "text"
						}
					]
				},
				"url": {
					"raw": "http://127.0.0.1:8000/message/2152d20f-a426-402f-bebd-72d5d2798dd8",
					"protocol": "http",
					"host": [
						"127",
						"0",
						"0",
						"1"
					],
					"port": "8000",
					"path": [
						"message",
						"2152d20f-a426-402f-bebd-72d5d2798dd8"
					]
				}
			},
			"response": []
		},
		{
			"name": "Notify One Message",
			"request": {
				"method": "GET",
				"header": [],
				"body": {},
				"url": {
					"raw": "http://127.0.0.1:8000/notify/f54f37be-37bb-4eb6-a731-3838c3cc49de",
					"protocol": "http",
					"host": [
						"127",
						"0",
						"0",
						"1"
					],
					"port": "8000",
					"path": [
						"notify",
						"f54f37be-37bb-4eb6-a731-3838c3cc49de"
					]
				}
			},
			"response": []
		},
		{
			"name": "Notify All Messages",
			"request": {
				"method": "GET",
				"header": [],
				"body": {},
				"url": {
					"raw": "http://127.0.0.1:8000/notify",
					"protocol": "http",
					"host": [
						"127",
						"0",
						"0",
						"1"
					],
					"port": "8000",
					"path": [
						"notify"
					]
				}
			},
			"response": []
		}
	]
}